{
  "appPageId" : "d4b9d053-8b4e-4256-9c48-81702c82945f",
  "componentName" : "siteforce:sldsOneColLayout",
  "dataProviders" : [ ],
  "id" : "ec030b34-688f-4426-a485-7f483b563089",
  "label" : "User Settings",
  "regions" : [ {
    "id" : "35c083f0-6381-4300-9556-b1f62c4d463b",
    "regionName" : "header",
    "type" : "region"
  }, {
    "components" : [ {
      "componentAttributes" : {
        "accountSectionTitle" : "Account",
        "accountTabName" : "Account Management",
        "connectedSourcesTabName" : "Connected Sources",
        "deleteAccountButtonTitle" : "Deactivate My Account",
        "deleteAccountConfirmationPopupBody" : "After you deactivate your account, you'll lose access to this site.",
        "deleteAccountConfirmationPopupButtonTitle" : "Got It",
        "deleteAccountConfirmationPopupTitle" : "Deactivate your account?",
        "deleteAccountErrorMessage" : "Something went wrong. Contact your site administrator.",
        "deleteAccountSectionTitle" : "Deactivate Account",
        "emailNotificationsTitle" : "Email Notifications",
        "emailSectionDescText" : "When email notifications are enabled, email me when someone:",
        "hideAccountDeleteSection" : true,
        "hideChatterNotificationSettings" : false,
        "hideConnectedSources" : false,
        "hideEmailNotificationSettings" : false,
        "hideProfileVisibilitySettings" : false,
        "id" : "{!recordId}",
        "locationTitle" : "Location",
        "profileSectionDescText" : "Customize who is able to see what on your profile page",
        "profileSectionToolTipText" : "Restricted: Visible to the employees of the company that created the site. Members: Visible to logged-in members. Public: Visible to anyone viewing pages that don't require login.",
        "profileVisibilityTitle" : "Profile Visibility",
        "settingsPageTitle" : "My Settings"
      },
      "componentName" : "forceCommunity:userSettingsCustomizable",
      "id" : "680afa09-9581-4d35-b3e3-d53dda994f3a",
      "renderPriority" : "NEUTRAL",
      "renditionMap" : { },
      "type" : "component"
    } ],
    "id" : "57a3acc3-0764-43af-aebd-245f075531fe",
    "regionName" : "content",
    "type" : "region"
  }, {
    "id" : "b900bef1-e285-4d7f-8785-4dbc31aab8a9",
    "regionName" : "footer",
    "type" : "region"
  } ],
  "themeLayoutType" : "Inner",
  "type" : "view",
  "viewType" : "usersettings"
}