{
  "activeBrandingSetId" : "5609e829-18a9-4295-bff7-1eebb62341ab",
  "customCSS" : "",
  "developerName" : "webster",
  "id" : "a76d6c9c-6b4c-4563-9b52-cb416fc59e0f",
  "label" : "Webster",
  "layouts" : {
    "Home" : "7d171add-a17c-4c53-ae34-cf5a62a122bd",
    "Inner" : "85de6c25-ca05-46c6-8f10-7503823b35df",
    "Login" : "4887c360-688f-4c4f-95f8-4ff63ff9c409",
    "ServiceNotAvailable" : "8f8a1bd2-7515-4ea5-b7d4-6fe90a8e489e"
  },
  "type" : "theme",
  "views" : [ {
    "componentAttributes" : { },
    "componentName" : "salesforceIdentity:loginBody2",
    "id" : "4887c360-688f-4c4f-95f8-4ff63ff9c409",
    "label" : "Login",
    "regions" : [ {
      "id" : "a30cb567-e013-44df-99ac-9dc37d6e7ffa",
      "regionName" : "header",
      "type" : "region"
    }, {
      "id" : "f273226b-8149-436e-a87d-cb050476bf61",
      "regionName" : "content",
      "type" : "region"
    }, {
      "id" : "c7849436-b21b-4f16-a667-ed8af1748169",
      "regionName" : "footer",
      "type" : "region"
    } ],
    "type" : "view"
  }, {
    "componentAttributes" : {
      "fixedPageWidth" : 1440,
      "headerBgColor" : "rgba(28, 22, 28, 0.9)",
      "isHeaderPinned" : false,
      "isHeroUnderHeader" : false,
      "isPageWidthFixed" : true,
      "showHeader" : true,
      "showHero" : false
    },
    "componentName" : "siteforce:themeLayoutStarter",
    "id" : "85de6c25-ca05-46c6-8f10-7503823b35df",
    "label" : "Default",
    "regions" : [ {
      "components" : [ {
        "componentAttributes" : {
          "background" : "background: #281f23 url(/sfsites/assets/themes/webster-background.jpg) top center /cover",
          "backgroundOverlayColor" : "rgba(0, 0, 0, 0.5)",
          "borderBottomColor" : "rgba(0, 0, 0, 0.5)",
          "centerAlignLogo" : false,
          "collapseNavMenu" : false,
          "containHeader" : true,
          "containHeaderWidth" : 1440,
          "dropdownBackgroundColor" : "#FFFFFF",
          "dropdownBackgroundHoverColor" : "",
          "dropdownBorderColor" : "#F0F0F0",
          "dropdownTextColor" : "",
          "dropdownTextHoverColor" : "",
          "headerHeight" : 24,
          "linkActiveBorderColor" : "",
          "linkColor" : "#FFFFFF",
          "linkHoverColor" : "rgba(255, 255, 255, 0.95)",
          "linkTextShadowColor" : "rgba(0, 0, 0, 0.95)",
          "logoWidth" : 169,
          "searchStyle" : "collapsed",
          "showAppLauncher" : false,
          "showNavMenuOnLeft" : true,
          "showNotifications" : true,
          "showProfileMenu" : true,
          "showSearch" : true
        },
        "componentName" : "forceCommunity:themeHeaderCompact",
        "id" : "69d2eab2-66e7-493b-8563-0a670060622a",
        "regions" : [ {
          "components" : [ {
            "componentAttributes" : {
              "buttonBackgroundColor" : "",
              "buttonBackgroundHoverColor" : "",
              "buttonBorderColor" : "rgba(240, 240, 240, 0)",
              "buttonBorderRadius" : 14,
              "buttonText" : "Log in",
              "buttonTextColor" : "",
              "buttonTextHoverColor" : "",
              "customizableUserProfileMenuEditor" : "Default_User_Profile_Menu3",
              "menuStyleSettings" : "{\"selectedMenuStyleSetting\":\"iconOnly\",\"selectedIconSetting\":\"userAvatar\",\"includeCompanyName\":false,\"selectedTextOrientationSetting\":\"right\"}"
            },
            "componentName" : "forceCommunity:customizableUserProfileMenu",
            "id" : "fef13fac-92be-450f-800b-3230b4cc58c9",
            "renditionMap" : { },
            "type" : "component"
          } ],
          "id" : "1fb9f7de-1877-449d-b196-45492ed42bd4",
          "regionName" : "themeHeaderProfileMenu",
          "type" : "region"
        }, {
          "components" : [ {
            "componentAttributes" : {
              "backgroundColor" : "#FFFFFF",
              "borderColor" : "#FFFFFF",
              "borderRadius" : 0,
              "borderStyle" : "outline",
              "buttonColor" : "",
              "buttonHoverColor" : "",
              "crossObjectTypeaheadApiNames" : "",
              "iconColor" : "rgba(0, 0, 0, 0.8)",
              "placeholderText" : "Search...",
              "placeholderTextColor" : "rgba(0, 0, 0, 0.6)",
              "showInputFocusOutline" : true,
              "showSearchButton" : false,
              "textColor" : "rgba(0, 0, 0, 0.8)",
              "typeaheadResultMax" : 5,
              "useTypeahead" : true
            },
            "componentName" : "forceCommunity:themeSearch",
            "id" : "78a7ba61-d15e-4add-8c42-93c3311139b4",
            "renditionMap" : { },
            "type" : "component"
          } ],
          "id" : "54c6538d-b4b0-464f-a54f-a6cdc103bf4c",
          "regionName" : "search",
          "type" : "region"
        }, {
          "components" : [ {
            "componentAttributes" : {
              "navAlignment" : "right",
              "navItemThreshold" : 5,
              "navigationMenuEditorRefresh" : ""
            },
            "componentName" : "forceCommunity:themeNav",
            "id" : "43a37702-932b-48e6-a09a-a2a57b2b7193",
            "renditionMap" : { },
            "type" : "component"
          } ],
          "id" : "938394fd-015f-426b-b012-77bf7e4da5ce",
          "regionName" : "nav",
          "type" : "region"
        }, {
          "id" : "568d83d5-e2d4-41c3-a33f-2feb2b8775c7",
          "regionName" : "cartIcon",
          "type" : "region"
        } ],
        "renditionMap" : { },
        "type" : "component"
      } ],
      "id" : "5a343aca-bb8d-4e9f-8580-66b9f9e1fa5f",
      "regionName" : "themeHeader",
      "type" : "region"
    }, {
      "components" : [ {
        "componentAttributes" : {
          "bgImage" : "background: #281f23",
          "bgOverlayColor" : "rgba(0, 0, 0, 0.5)",
          "captionText" : "",
          "captionTextColor" : "#FFFFFF",
          "captionTextShadowColor" : "rgba(0, 0, 0, 0.5)",
          "contentAlignment" : "center",
          "contentWidth" : 65,
          "ctaBtnOneBgColor" : "",
          "ctaBtnOneBgHoverColor" : "",
          "ctaBtnOneBorderColor" : "rgba(0, 0, 0, 0)",
          "ctaBtnOneOpenNewTab" : false,
          "ctaBtnOneText" : "Show Me",
          "ctaBtnOneTextColor" : "",
          "ctaBtnOneTextHoverColor" : "",
          "ctaBtnOneUrl" : "",
          "ctaBtnRadius" : 25,
          "ctaBtnTwoBgColor" : "rgba(255, 255, 255, 0)",
          "ctaBtnTwoBgHoverColor" : "#FFFFFF",
          "ctaBtnTwoBorderColor" : "#FFFFFF",
          "ctaBtnTwoOpenNewTab" : false,
          "ctaBtnTwoText" : "Learn More",
          "ctaBtnTwoTextColor" : "#FFFFFF",
          "ctaBtnTwoTextHoverColor" : "rgba(0, 0, 0, 0.8)",
          "ctaBtnTwoUrl" : "",
          "ctaShowBtnOne" : true,
          "ctaShowBtnTwo" : true,
          "fixedHeroWidth" : true,
          "heroHeight" : 150,
          "heroWidth" : 1440,
          "showCaption" : false,
          "showSubtitle" : false,
          "showTitle" : true,
          "subtitleText" : "",
          "subtitleTextColor" : "#FFFFFF",
          "subtitleTextShadowColor" : "rgba(0, 0, 0, 0.5)",
          "titleText" : "What can we help you with?",
          "titleTextColor" : "#FFFFFF",
          "titleTextShadowColor" : "rgba(0, 0, 0, 0.5)",
          "type" : "showSearch"
        },
        "componentName" : "forceCommunity:themeHeroStarter",
        "id" : "8f99801f-75bb-4b01-99b8-e4e621535e26",
        "regions" : [ {
          "components" : [ {
            "componentAttributes" : {
              "backgroundColor" : "#FFFFFF",
              "borderColor" : "rgba(0, 0, 0, 0)",
              "borderRadius" : 25,
              "borderStyle" : "outline",
              "buttonColor" : "",
              "buttonHoverColor" : "",
              "crossObjectTypeaheadApiNames" : "",
              "iconColor" : "#FFFFFF",
              "placeholderText" : "Ask a question...",
              "placeholderTextColor" : "rgba(0, 0, 0, 0.6)",
              "publicDropdownBackgroundColor" : "#FFFFFF",
              "publicDropdownBackgroundHoverColor" : "",
              "publicDropdownBorderColor" : "#F0F0F0",
              "publicDropdownTextColor" : "",
              "publicDropdownTextHoverColor" : "",
              "showInputFocusOutline" : true,
              "showSearchButton" : true,
              "textColor" : "rgba(0, 0, 0, 0.8)",
              "typeaheadResultMax" : 6,
              "useTypeahead" : true
            },
            "componentName" : "forceCommunity:themeSearchHero",
            "id" : "f728e4da-aab3-46e8-b1e0-daac5afa887e",
            "renditionMap" : { },
            "type" : "component"
          } ],
          "id" : "e4cb6b3b-b6e3-49a0-934e-289a52bfdf3e",
          "regionName" : "search",
          "type" : "region"
        } ],
        "renditionMap" : { },
        "type" : "component"
      } ],
      "id" : "68c62016-e50c-4105-a7cc-997e65ec89d3",
      "regionName" : "themeHero",
      "type" : "region"
    }, {
      "id" : "4ed025a7-95ac-433e-8bd7-cf49f8e390a7",
      "regionName" : "themeFooter",
      "type" : "region"
    } ],
    "type" : "view"
  }, {
    "componentAttributes" : {
      "fixedPageWidth" : 1440,
      "headerBgColor" : "rgba(28, 22, 28, 0.9)",
      "isHeaderPinned" : false,
      "isHeroUnderHeader" : true,
      "isPageWidthFixed" : true,
      "showHeader" : true,
      "showHero" : true
    },
    "componentName" : "siteforce:themeLayoutStarter",
    "id" : "7d171add-a17c-4c53-ae34-cf5a62a122bd",
    "label" : "Home",
    "regions" : [ {
      "components" : [ {
        "componentAttributes" : {
          "background" : "background: rgba(40,31,35,0)",
          "backgroundOverlayColor" : "rgba(0, 0, 0, 0.5)",
          "borderBottomColor" : "rgba(0, 0, 0, 0)",
          "centerAlignLogo" : false,
          "collapseNavMenu" : false,
          "containHeader" : true,
          "containHeaderWidth" : 1440,
          "dropdownBackgroundColor" : "#FFFFFF",
          "dropdownBackgroundHoverColor" : "",
          "dropdownBorderColor" : "#F0F0F0",
          "dropdownTextColor" : "",
          "dropdownTextHoverColor" : "",
          "headerHeight" : 24,
          "linkActiveBorderColor" : "",
          "linkColor" : "#FFFFFF",
          "linkHoverColor" : "rgba(255, 255, 255, 0.95)",
          "linkTextShadowColor" : "rgba(0, 0, 0, 0.95)",
          "logoWidth" : 169,
          "searchStyle" : "collapsed",
          "showAppLauncher" : false,
          "showNavMenuOnLeft" : true,
          "showNotifications" : true,
          "showProfileMenu" : true,
          "showSearch" : false
        },
        "componentName" : "forceCommunity:themeHeaderCompact",
        "id" : "62969f5a-4ae0-4aac-8755-587984660657",
        "regions" : [ {
          "components" : [ {
            "componentAttributes" : {
              "buttonBackgroundColor" : "",
              "buttonBackgroundHoverColor" : "",
              "buttonBorderColor" : "rgba(240, 240, 240, 0)",
              "buttonBorderRadius" : 14,
              "buttonText" : "Log in",
              "buttonTextColor" : "",
              "buttonTextHoverColor" : "",
              "customizableUserProfileMenuEditor" : "Default_User_Profile_Menu3",
              "menuStyleSettings" : "{\"selectedMenuStyleSetting\":\"iconOnly\",\"selectedIconSetting\":\"userAvatar\",\"includeCompanyName\":false,\"selectedTextOrientationSetting\":\"right\"}"
            },
            "componentName" : "forceCommunity:customizableUserProfileMenu",
            "id" : "d17ce0c4-1f2b-457f-88c7-26e985cec73e",
            "renditionMap" : { },
            "type" : "component"
          } ],
          "id" : "78cc943c-3a94-4311-a27c-a11ad3dc783a",
          "regionName" : "themeHeaderProfileMenu",
          "type" : "region"
        }, {
          "components" : [ {
            "componentAttributes" : {
              "backgroundColor" : "#FFFFFF",
              "borderColor" : "#FFFFFF",
              "borderRadius" : 0,
              "borderStyle" : "outline",
              "buttonColor" : "",
              "buttonHoverColor" : "",
              "crossObjectTypeaheadApiNames" : "",
              "iconColor" : "rgba(0, 0, 0, 0.8)",
              "placeholderText" : "Search...",
              "placeholderTextColor" : "rgba(0, 0, 0, 0.6)",
              "showInputFocusOutline" : true,
              "showSearchButton" : false,
              "textColor" : "rgba(0, 0, 0, 0.8)",
              "typeaheadResultMax" : 5,
              "useTypeahead" : true
            },
            "componentName" : "forceCommunity:themeSearch",
            "id" : "0fe692ee-64f3-4a08-bff4-94943965a305",
            "renditionMap" : { },
            "type" : "component"
          } ],
          "id" : "0e2af144-6294-4984-8889-b22bf09e077f",
          "regionName" : "search",
          "type" : "region"
        }, {
          "components" : [ {
            "componentAttributes" : {
              "navAlignment" : "left",
              "navItemThreshold" : 5,
              "navigationMenuEditorRefresh" : "Default_User_Profile_Menu3"
            },
            "componentName" : "forceCommunity:themeNav",
            "id" : "e6f28219-9e9e-4869-8b95-edcb56a60dcc",
            "renditionMap" : { },
            "type" : "component"
          } ],
          "id" : "de690ede-4051-46c1-b7ae-240095d36180",
          "regionName" : "nav",
          "type" : "region"
        }, {
          "id" : "4920d821-a13a-4c3c-b632-165186727631",
          "regionName" : "cartIcon",
          "type" : "region"
        } ],
        "renditionMap" : { },
        "type" : "component"
      } ],
      "id" : "2df4878d-34ec-41ca-bfc8-00dc882b941d",
      "regionName" : "themeHeader",
      "type" : "region"
    }, {
      "components" : [ {
        "componentAttributes" : {
          "bgImage" : "background: #281f23",
          "bgOverlayColor" : "rgba(0, 0, 0, 0.5)",
          "captionText" : "",
          "captionTextColor" : "#FFFFFF",
          "captionTextShadowColor" : "rgba(0, 0, 0, 0.5)",
          "contentAlignment" : "center",
          "contentWidth" : 62,
          "ctaBtnOneBgColor" : "",
          "ctaBtnOneBgHoverColor" : "",
          "ctaBtnOneBorderColor" : "rgba(0, 0, 0, 0)",
          "ctaBtnOneOpenNewTab" : false,
          "ctaBtnOneText" : "Show Me",
          "ctaBtnOneTextColor" : "",
          "ctaBtnOneTextHoverColor" : "",
          "ctaBtnOneUrl" : "",
          "ctaBtnRadius" : 25,
          "ctaBtnTwoBgColor" : "rgba(255, 255, 255, 0)",
          "ctaBtnTwoBgHoverColor" : "#FFFFFF",
          "ctaBtnTwoBorderColor" : "#FFFFFF",
          "ctaBtnTwoOpenNewTab" : false,
          "ctaBtnTwoText" : "Learn More",
          "ctaBtnTwoTextColor" : "#FFFFFF",
          "ctaBtnTwoTextHoverColor" : "rgba(0, 0, 0, 0.8)",
          "ctaBtnTwoUrl" : "",
          "ctaShowBtnOne" : true,
          "ctaShowBtnTwo" : true,
          "fixedHeroWidth" : true,
          "heroHeight" : 150,
          "heroWidth" : 1295,
          "showCaption" : false,
          "showSubtitle" : false,
          "showTitle" : true,
          "subtitleText" : "",
          "subtitleTextColor" : "#FFFFFF",
          "subtitleTextShadowColor" : "rgba(0, 0, 0, 0.5)",
          "titleText" : "Welcome to ES India.",
          "titleTextColor" : "#FFFFFF",
          "titleTextShadowColor" : "rgba(0, 0, 0, 0.5)",
          "type" : "showSearch"
        },
        "componentName" : "forceCommunity:themeHeroStarter",
        "id" : "7c21bc39-8a7e-4b32-8500-af2f940bb137",
        "regions" : [ {
          "components" : [ {
            "componentAttributes" : {
              "contineActionLabel" : "Ask the community",
              "continueLabel" : "Don’t see it?",
              "crossObjectTypeaheadApiNames" : "",
              "disableCrossObjectRelevance" : false,
              "enableAutocomplete" : true,
              "maxNumberOfResults" : 6,
              "placeholder" : "Search...",
              "questionResultsFirst" : false,
              "showContinueAction" : true,
              "showDetails" : false,
              "showTopics" : true,
              "signInActionLabel" : "Sign in to ask the community"
            },
            "componentName" : "forceCommunity:searchBox",
            "id" : "262c0a75-15cc-4006-abe7-f4201e763af9",
            "renditionMap" : { },
            "type" : "component"
          } ],
          "id" : "6c4f5cf9-eec5-42e1-8f84-ae2af5e365b1",
          "regionName" : "search",
          "type" : "region"
        } ],
        "renditionMap" : { },
        "type" : "component"
      } ],
      "id" : "82134169-b76f-4914-8d1f-febb00209173",
      "regionName" : "themeHero",
      "type" : "region"
    }, {
      "id" : "e1e2d451-9c9e-4296-8f17-0c282816cd39",
      "regionName" : "themeFooter",
      "type" : "region"
    } ],
    "type" : "view"
  }, {
    "componentAttributes" : {
      "fixedPageWidth" : 1440,
      "headerBgColor" : "rgba(0, 0, 0, 0)",
      "isHeaderPinned" : false,
      "isHeroUnderHeader" : false,
      "isPageWidthFixed" : true,
      "showHeader" : true,
      "showHero" : true
    },
    "componentName" : "siteforce:themeLayoutStarter",
    "id" : "8f8a1bd2-7515-4ea5-b7d4-6fe90a8e489e",
    "label" : "ServiceNotAvailable",
    "regions" : [ {
      "id" : "cfba1bdb-e20e-46da-b530-ee48e9a2ec5a",
      "regionName" : "themeHeader",
      "type" : "region"
    }, {
      "id" : "f7b16154-db7f-4265-97c0-dc33afccdcc6",
      "regionName" : "themeFooter",
      "type" : "region"
    } ],
    "type" : "view"
  } ]
}