{
  "appPageId" : "fc7479fa-1a96-4e20-a838-94b46dded155",
  "componentName" : "siteforce:sldsOneColLayout",
  "dataProviders" : [ ],
  "id" : "8e3d852e-dd9f-4f73-bf6f-c728b3535c4e",
  "label" : "User Profile",
  "regions" : [ {
    "id" : "4ba0ca3e-d57f-4cc7-97d0-312cb8fd7303",
    "regionName" : "header",
    "type" : "region"
  }, {
    "components" : [ {
      "componentAttributes" : {
        "caseCreateLabel" : "Create Case",
        "caseFilterName" : "AllOpenCases",
        "caseHeaderLabel" : "My Cases",
        "casesTabLabel" : "Cases",
        "detailsTabLabel" : "Details",
        "feedTabLabel" : "Feed",
        "knowledgeableAboutTitle" : "Knows About",
        "maxTopics" : 5,
        "recognitionbuttonLabel" : "Give",
        "relatedTabLabel" : "Related",
        "showAllUpdates" : false,
        "showBadges" : true,
        "showFullPhotoAsCircle" : true,
        "showKnowledgeableAbout" : true,
        "showRelatedList" : true,
        "showReputationInInfluenceCard" : false,
        "showStats" : true,
        "userBadgesTitle" : "Recognition Badges",
        "userId" : "{!recordId}",
        "userStatsTitle" : "Influence"
      },
      "componentName" : "forceCommunity:userRecordHome",
      "id" : "f9e06d64-226d-4152-ae7d-fc6fa7dc37af",
      "renderPriority" : "NEUTRAL",
      "renditionMap" : { },
      "type" : "component"
    } ],
    "id" : "e47a09a4-ef9d-46ab-a25a-85d42d1aa8aa",
    "regionName" : "content",
    "type" : "region"
  }, {
    "id" : "d4fe12db-fe29-413a-8ece-2d38b1aedc82",
    "regionName" : "footer",
    "type" : "region"
  } ],
  "themeLayoutType" : "Inner",
  "type" : "view",
  "viewType" : "detail-005"
}